baidu_url_submit/__init__.py
baidu_url_submit/submit.py
baidu_url_submit-1.0.0.dist-info/LICENSE.txt
baidu_url_submit-1.0.0.dist-info/METADATA
baidu_url_submit-1.0.0.dist-info/WHEEL
baidu_url_submit-1.0.0.dist-info/top_level.txt
baidu_url_submit-1.0.0.dist-info/RECORD
