Metadata-Version: 2.1
Name: baidu-url-submit
Version: 1.0.0
Summary: submit url to baidu.
Home-page: https://github.com/wansho/baidu-url-submit
Author: wansho
Author-email: wanshojs@hotmail.com
License: UNKNOWN
Platform: UNKNOWN
Classifier: Programming Language :: Python :: 3
Classifier: License :: OSI Approved :: MIT License
Classifier: Operating System :: OS Independent
